MANIFEST.in
README.md
setup.cfg
setup.py
speexdsp.egg-info/PKG-INFO
speexdsp.egg-info/SOURCES.txt
speexdsp.egg-info/dependency_links.txt
speexdsp.egg-info/top_level.txt
src/__init__.py
src/echo_canceller.cpp
src/echo_canceller.h
src/speexdsp.i
src/speexdsp.py